setup.py
port_history_plugin/__init__.py
port_history_plugin/choices.py
port_history_plugin/filters.py
port_history_plugin/forms.py
port_history_plugin/models.py
port_history_plugin/navigation.py
port_history_plugin/signals.py
port_history_plugin/tables.py
port_history_plugin/urls.py
port_history_plugin/views.py
port_history_plugin.egg-info/PKG-INFO
port_history_plugin.egg-info/SOURCES.txt
port_history_plugin.egg-info/dependency_links.txt
port_history_plugin.egg-info/requires.txt
port_history_plugin.egg-info/top_level.txt
port_history_plugin/management/__init__.py
port_history_plugin/management/commands/__init__.py
port_history_plugin/management/commands/porthistory.py
port_history_plugin/migrations/0001_initial.py
port_history_plugin/migrations/__init__.py